{
  "schemaVersion": 1,
  "bundlePath": "trusted_ca_bundle.pem",
  "metadataPath": "trusted_ca_bundle_meta.json",
  "bundleSha256": "c403d4a5dfd974aab5bd83c71ed983c9422acd1008cec293ba1fd8062203046f",
  "metadataSha256": "c2ce3f232d09ea58ac35fb20dc2de37c8e31fb76719df3cd51c64a10bad176b5",
  "certificateCount": 21,
  "generatedAt": "2026-05-22T22:23:10Z",
  "expiresAt": "2026-06-05T22:23:10Z",
  "keyId": "a2a34fe4734b9c79",
  "signatureAlgorithm": "SHA384withECDSA",
  "hosts": [
    "app.unimol.it",
    "unimol.esse3.cineca.it",
    "sync.faufas.it",
    "trasporti.unimol.it",
    "learn.unimol.it",
    "api.github.com",
    "github.com",
    "raw.githubusercontent.com",
    "avatars.githubusercontent.com",
    "objects.githubusercontent.com",
    "github-releases.githubusercontent.com",
    "codeload.github.com",
    "tile.openstreetmap.org",
    "router.project-osrm.org",
    "uniaappauthorization.antobot.info"
  ],
  "signature": "MGUCMQDOaw1ekXG9tNU2gZRkhNCw3uIQz/R8NqVu91ff3QZsMNSdA/tP+C5Mcm7T3UGcP8ECMC3cXg8AKKJB4mlAbwZ7kqJ29yyWgu1sjJFxvlJY+eIoZOzZeOuY2rhEZATbUojTTg=="
}
